README.md
setup.py
test/test_cli.py
webhook_cli/__init__.py
webhook_cli/_helper.py
webhook_cli/cli.py
webhook_cli.egg-info/PKG-INFO
webhook_cli.egg-info/SOURCES.txt
webhook_cli.egg-info/dependency_links.txt
webhook_cli.egg-info/entry_points.txt
webhook_cli.egg-info/not-zip-safe
webhook_cli.egg-info/requires.txt
webhook_cli.egg-info/top_level.txt
webhook_cli/ext/__init__.py
webhook_cli/ext/dingtalk.py