Metadata-Version: 2.1
Name: webhook-cli
Version: 2024.4.17
Summary: webhook通知命令行工具
Home-page: https://git.minieye.tech/nico/wehook-cli
Author: Nico Ning
Author-email: ningrong@minieye.cc
License: MIT
Platform: any
Classifier: Development Status :: 4 - Beta
Classifier: Intended Audience :: Developers
Classifier: Topic :: Software Development :: Build Tools
Classifier: License :: OSI Approved :: MIT License
Classifier: Operating System :: OS Independent
Classifier: Programming Language :: Python :: 3
Classifier: Programming Language :: Python :: 3.6
Classifier: Programming Language :: Python :: 3.7
Classifier: Programming Language :: Python :: 3.8
Classifier: Programming Language :: Python :: 3.9
Classifier: Programming Language :: Python :: 3.10
